rscli/__init__.py
rscli/__main__.py
rscli/conf.py
rscli/page.py
runstatus_cli-0.3.dist-info/DESCRIPTION.rst
runstatus_cli-0.3.dist-info/METADATA
runstatus_cli-0.3.dist-info/RECORD
runstatus_cli-0.3.dist-info/WHEEL
runstatus_cli-0.3.dist-info/entry_points.txt
runstatus_cli-0.3.dist-info/metadata.json
runstatus_cli-0.3.dist-info/top_level.txt
