Metadata-Version: 2.0
Name: runstatus-cli
Version: 0.3
Summary: UNKNOWN
Home-page: UNKNOWN
Author: UNKNOWN
Author-email: UNKNOWN
License: UNKNOWN
Platform: UNKNOWN
Requires-Dist: click (==6.7)
Requires-Dist: requests (==2.14.2)
Requires-Dist: requests-exoscale-auth (==1.0)
